{"config":{"output_file":null,"full_docs":false,"pub_only":false,"reachable_only":false,"distro_crate":false,"signatures":false,"borrow_data":false},"version":"0.19.0","compilation":{"directory":"c:\\Users\\pictu\\Documents\\Study\\Rust\\AIZU_ONLINE_JUDGE\\Courses\\Lesson-ALDS1\\ALDS1_1_A","program":"C:\\Users\\pictu\\.rustup\\toolchains\\stable-x86_64-pc-windows-msvc\\bin\\rls.exe","arguments":[],"output":"c:\\Users\\pictu\\Documents\\Study\\Rust\\AIZU_ONLINE_JUDGE\\Courses\\Lesson-ALDS1\\ALDS1_1_A\\target\\rls\\debug\\deps\\libALDS1_1_A-82716d46ce5019bf.rmeta"},"prelude":{"crate_id":{"name":"ALDS1_1_A","disambiguator":[6432113548573121193,5918999397818645580]},"crate_root":"src","external_crates":[{"file_name":"c:\\Users\\pictu\\Documents\\Study\\Rust\\AIZU_ONLINE_JUDGE\\Courses\\Lesson-ALDS1\\ALDS1_1_A\\src\\main.rs","num":1,"id":{"name":"std","disambiguator":[1921591330338517602,8002743023817837766]}},{"file_name":"c:\\Users\\pictu\\Documents\\Study\\Rust\\AIZU_ONLINE_JUDGE\\Courses\\Lesson-ALDS1\\ALDS1_1_A\\src\\main.rs","num":2,"id":{"name":"core","disambiguator":[3294562336267099064,32966444439847392]}},{"file_name":"c:\\Users\\pictu\\Documents\\Study\\Rust\\AIZU_ONLINE_JUDGE\\Courses\\Lesson-ALDS1\\ALDS1_1_A\\src\\main.rs","num":3,"id":{"name":"compiler_builtins","disambiguator":[8997478989526601172,15466949633016966289]}},{"file_name":"c:\\Users\\pictu\\Documents\\Study\\Rust\\AIZU_ONLINE_JUDGE\\Courses\\Lesson-ALDS1\\ALDS1_1_A\\src\\main.rs","num":4,"id":{"name":"rustc_std_workspace_core","disambiguator":[2630917957276446109,8658156290826251556]}},{"file_name":"c:\\Users\\pictu\\Documents\\Study\\Rust\\AIZU_ONLINE_JUDGE\\Courses\\Lesson-ALDS1\\ALDS1_1_A\\src\\main.rs","num":5,"id":{"name":"alloc","disambiguator":[16592919627580665262,9528133364691589515]}},{"file_name":"c:\\Users\\pictu\\Documents\\Study\\Rust\\AIZU_ONLINE_JUDGE\\Courses\\Lesson-ALDS1\\ALDS1_1_A\\src\\main.rs","num":6,"id":{"name":"libc","disambiguator":[12745094628986209607,10518202857406436678]}},{"file_name":"c:\\Users\\pictu\\Documents\\Study\\Rust\\AIZU_ONLINE_JUDGE\\Courses\\Lesson-ALDS1\\ALDS1_1_A\\src\\main.rs","num":7,"id":{"name":"unwind","disambiguator":[12421643217715303902,5448498891032173630]}},{"file_name":"c:\\Users\\pictu\\Documents\\Study\\Rust\\AIZU_ONLINE_JUDGE\\Courses\\Lesson-ALDS1\\ALDS1_1_A\\src\\main.rs","num":8,"id":{"name":"cfg_if","disambiguator":[10471275659107711445,16777480585464664117]}},{"file_name":"c:\\Users\\pictu\\Documents\\Study\\Rust\\AIZU_ONLINE_JUDGE\\Courses\\Lesson-ALDS1\\ALDS1_1_A\\src\\main.rs","num":9,"id":{"name":"hashbrown","disambiguator":[5556840401016198219,10246883469141694681]}},{"file_name":"c:\\Users\\pictu\\Documents\\Study\\Rust\\AIZU_ONLINE_JUDGE\\Courses\\Lesson-ALDS1\\ALDS1_1_A\\src\\main.rs","num":10,"id":{"name":"rustc_std_workspace_alloc","disambiguator":[5351773000290944944,5461204872568622329]}},{"file_name":"c:\\Users\\pictu\\Documents\\Study\\Rust\\AIZU_ONLINE_JUDGE\\Courses\\Lesson-ALDS1\\ALDS1_1_A\\src\\main.rs","num":11,"id":{"name":"rustc_demangle","disambiguator":[1406896991597352872,16715998803959789672]}},{"file_name":"c:\\Users\\pictu\\Documents\\Study\\Rust\\AIZU_ONLINE_JUDGE\\Courses\\Lesson-ALDS1\\ALDS1_1_A\\src\\main.rs","num":12,"id":{"name":"panic_unwind","disambiguator":[16017799561494711091,10322761666972095232]}},{"file_name":"c:\\Users\\pictu\\Documents\\Study\\Rust\\AIZU_ONLINE_JUDGE\\Courses\\Lesson-ALDS1\\ALDS1_1_A\\src\\main.rs","num":13,"id":{"name":"test","disambiguator":[940063802747980962,9777064951882803514]}},{"file_name":"c:\\Users\\pictu\\Documents\\Study\\Rust\\AIZU_ONLINE_JUDGE\\Courses\\Lesson-ALDS1\\ALDS1_1_A\\src\\main.rs","num":14,"id":{"name":"getopts","disambiguator":[2898387419533831248,12755878832390804103]}},{"file_name":"c:\\Users\\pictu\\Documents\\Study\\Rust\\AIZU_ONLINE_JUDGE\\Courses\\Lesson-ALDS1\\ALDS1_1_A\\src\\main.rs","num":15,"id":{"name":"rustc_std_workspace_std","disambiguator":[6890851750537788701,9942309285331080021]}},{"file_name":"c:\\Users\\pictu\\Documents\\Study\\Rust\\AIZU_ONLINE_JUDGE\\Courses\\Lesson-ALDS1\\ALDS1_1_A\\src\\main.rs","num":16,"id":{"name":"unicode_width","disambiguator":[7717310477677733230,10637985392830860985]}},{"file_name":"c:\\Users\\pictu\\Documents\\Study\\Rust\\AIZU_ONLINE_JUDGE\\Courses\\Lesson-ALDS1\\ALDS1_1_A\\src\\main.rs","num":17,"id":{"name":"term","disambiguator":[17994536268644905883,12638637972235686966]}}],"span":{"file_name":"src\\main.rs","byte_start":0,"byte_end":866,"line_start":1,"line_end":25,"column_start":1,"column_end":2}},"imports":[],"defs":[{"kind":"Mod","id":{"krate":0,"index":0},"span":{"file_name":"src\\main.rs","byte_start":0,"byte_end":866,"line_start":1,"line_end":25,"column_start":1,"column_end":2},"name":"","qualname":"::","value":"src\\main.rs","parent":null,"children":[{"krate":0,"index":1},{"krate":0,"index":2},{"krate":0,"index":3},{"krate":0,"index":5}],"decl_id":null,"docs":"","sig":null,"attributes":[]},{"kind":"Function","id":{"krate":0,"index":3},"span":{"file_name":"src\\main.rs","byte_start":3,"byte_end":7,"line_start":1,"line_end":1,"column_start":4,"column_end":8},"name":"main","qualname":"::main","value":"fn main()","parent":null,"children":[],"decl_id":null,"docs":"","sig":null,"attributes":[{"value":"allow(dead_code)","span":{"file_name":"src\\main.rs","byte_start":0,"byte_end":0,"line_start":1,"line_end":1,"column_start":1,"column_end":1}}]},{"kind":"Local","id":{"krate":0,"index":2147483651},"span":{"file_name":"src\\main.rs","byte_start":24,"byte_end":27,"line_start":2,"line_end":2,"column_start":13,"column_end":16},"name":"len","qualname":"len$HirId { owner: DefId(0:3 ~ ALDS1_1_A[5943]::main), local_id: 1 }","value":"std::string::String","parent":null,"children":[],"decl_id":null,"docs":"","sig":null,"attributes":[]},{"kind":"Local","id":{"krate":0,"index":1073741827},"span":{"file_name":"src\\main.rs","byte_start":108,"byte_end":112,"line_start":4,"line_end":4,"column_start":13,"column_end":17},"name":"nums","qualname":"nums$HirId { owner: DefId(0:3 ~ ALDS1_1_A[5943]::main), local_id: 2 }","value":"std::string::String","parent":null,"children":[],"decl_id":null,"docs":"","sig":null,"attributes":[]},{"kind":"Local","id":{"krate":0,"index":3221225475},"span":{"file_name":"src\\main.rs","byte_start":199,"byte_end":203,"line_start":7,"line_end":7,"column_start":13,"column_end":17},"name":"nums","qualname":"nums$HirId { owner: DefId(0:3 ~ ALDS1_1_A[5943]::main), local_id: 3 }","value":"std::vec::Vec<u64>","parent":null,"children":[],"decl_id":null,"docs":"","sig":null,"attributes":[]},{"kind":"Local","id":{"krate":0,"index":536870915},"span":{"file_name":"src\\main.rs","byte_start":281,"byte_end":282,"line_start":8,"line_end":8,"column_start":35,"column_end":36},"name":"c","qualname":"$HirId { owner: DefId(0:3 ~ ALDS1_1_A[5943]::main), local_id: 82 }::c","value":"&str","parent":null,"children":[],"decl_id":null,"docs":"","sig":null,"attributes":[]},{"kind":"Local","id":{"krate":0,"index":2516582403},"span":{"file_name":"src\\main.rs","byte_start":342,"byte_end":365,"line_start":9,"line_end":9,"column_start":21,"column_end":44},"name":"iter","qualname":"iter$HirId { owner: DefId(0:3 ~ ALDS1_1_A[5943]::main), local_id: 105 }","value":"std::iter::Enumerate<std::slice::Iter<u64>>","parent":null,"children":[],"decl_id":null,"docs":"","sig":null,"attributes":[]},{"kind":"Local","id":{"krate":0,"index":3120562179},"span":{"file_name":"src\\main.rs","byte_start":342,"byte_end":365,"line_start":9,"line_end":9,"column_start":21,"column_end":44},"name":"__next","qualname":"__next$HirId { owner: DefId(0:3 ~ ALDS1_1_A[5943]::main), local_id: 93 }","value":"(usize, &u64)","parent":null,"children":[],"decl_id":null,"docs":"","sig":null,"attributes":[]},{"kind":"Local","id":{"krate":0,"index":2046820355},"span":{"file_name":"src\\main.rs","byte_start":330,"byte_end":338,"line_start":9,"line_end":9,"column_start":9,"column_end":17},"name":"val","qualname":"val$HirId { owner: DefId(0:3 ~ ALDS1_1_A[5943]::main), local_id: 94 }","value":"(usize, &u64)","parent":null,"children":[],"decl_id":null,"docs":"","sig":null,"attributes":[]},{"kind":"Local","id":{"krate":0,"index":1610612739},"span":{"file_name":"src\\main.rs","byte_start":331,"byte_end":332,"line_start":9,"line_end":9,"column_start":10,"column_end":11},"name":"i","qualname":"i$HirId { owner: DefId(0:3 ~ ALDS1_1_A[5943]::main), local_id: 6 }","value":"usize","parent":null,"children":[],"decl_id":null,"docs":"","sig":null,"attributes":[]},{"kind":"Local","id":{"krate":0,"index":3758096387},"span":{"file_name":"src\\main.rs","byte_start":334,"byte_end":337,"line_start":9,"line_end":9,"column_start":13,"column_end":16},"name":"num","qualname":"num$HirId { owner: DefId(0:3 ~ ALDS1_1_A[5943]::main), local_id: 7 }","value":"&u64","parent":null,"children":[],"decl_id":null,"docs":"","sig":null,"attributes":[]},{"kind":"Local","id":{"krate":0,"index":1191182339},"span":{"file_name":"src\\main.rs","byte_start":465,"byte_end":478,"line_start":13,"line_end":13,"column_start":14,"column_end":27},"name":"iter","qualname":"iter$HirId { owner: DefId(0:3 ~ ALDS1_1_A[5943]::main), local_id: 226 }","value":"std::ops::Range<usize>","parent":null,"children":[],"decl_id":null,"docs":"","sig":null,"attributes":[]},{"kind":"Local","id":{"krate":0,"index":1795162115},"span":{"file_name":"src\\main.rs","byte_start":465,"byte_end":478,"line_start":13,"line_end":13,"column_start":14,"column_end":27},"name":"__next","qualname":"__next$HirId { owner: DefId(0:3 ~ ALDS1_1_A[5943]::main), local_id: 214 }","value":"usize","parent":null,"children":[],"decl_id":null,"docs":"","sig":null,"attributes":[]},{"kind":"Local","id":{"krate":0,"index":3942645763},"span":{"file_name":"src\\main.rs","byte_start":460,"byte_end":461,"line_start":13,"line_end":13,"column_start":9,"column_end":10},"name":"val","qualname":"val$HirId { owner: DefId(0:3 ~ ALDS1_1_A[5943]::main), local_id: 215 }","value":"usize","parent":null,"children":[],"decl_id":null,"docs":"","sig":null,"attributes":[]},{"kind":"Local","id":{"krate":0,"index":3489660931},"span":{"file_name":"src\\main.rs","byte_start":460,"byte_end":461,"line_start":13,"line_end":13,"column_start":9,"column_end":10},"name":"i","qualname":"i$HirId { owner: DefId(0:3 ~ ALDS1_1_A[5943]::main), local_id: 11 }","value":"usize","parent":null,"children":[],"decl_id":null,"docs":"","sig":null,"attributes":[]},{"kind":"Local","id":{"krate":0,"index":805306371},"span":{"file_name":"src\\main.rs","byte_start":497,"byte_end":498,"line_start":14,"line_end":14,"column_start":17,"column_end":18},"name":"j","qualname":"j$HirId { owner: DefId(0:3 ~ ALDS1_1_A[5943]::main), local_id: 12 }","value":"i64","parent":null,"children":[],"decl_id":null,"docs":"","sig":null,"attributes":[]},{"kind":"Local","id":{"krate":0,"index":2952790019},"span":{"file_name":"src\\main.rs","byte_start":535,"byte_end":538,"line_start":15,"line_end":15,"column_start":13,"column_end":16},"name":"key","qualname":"key$HirId { owner: DefId(0:3 ~ ALDS1_1_A[5943]::main), local_id: 13 }","value":"u64","parent":null,"children":[],"decl_id":null,"docs":"","sig":null,"attributes":[]},{"kind":"Local","id":{"krate":0,"index":1786773507},"span":{"file_name":"src\\main.rs","byte_start":749,"byte_end":772,"line_start":21,"line_end":21,"column_start":25,"column_end":48},"name":"iter","qualname":"iter$HirId { owner: DefId(0:3 ~ ALDS1_1_A[5943]::main), local_id: 342 }","value":"std::iter::Enumerate<std::slice::Iter<u64>>","parent":null,"children":[],"decl_id":null,"docs":"","sig":null,"attributes":[]},{"kind":"Local","id":{"krate":0,"index":1384120323},"span":{"file_name":"src\\main.rs","byte_start":749,"byte_end":772,"line_start":21,"line_end":21,"column_start":25,"column_end":48},"name":"__next","qualname":"__next$HirId { owner: DefId(0:3 ~ ALDS1_1_A[5943]::main), local_id: 330 }","value":"(usize, &u64)","parent":null,"children":[],"decl_id":null,"docs":"","sig":null,"attributes":[]},{"kind":"Local","id":{"krate":0,"index":3531603971},"span":{"file_name":"src\\main.rs","byte_start":737,"byte_end":745,"line_start":21,"line_end":21,"column_start":13,"column_end":21},"name":"val","qualname":"val$HirId { owner: DefId(0:3 ~ ALDS1_1_A[5943]::main), local_id: 331 }","value":"(usize, &u64)","parent":null,"children":[],"decl_id":null,"docs":"","sig":null,"attributes":[]},{"kind":"Local","id":{"krate":0,"index":4026531843},"span":{"file_name":"src\\main.rs","byte_start":738,"byte_end":739,"line_start":21,"line_end":21,"column_start":14,"column_end":15},"name":"i","qualname":"i$HirId { owner: DefId(0:3 ~ ALDS1_1_A[5943]::main), local_id: 15 }","value":"usize","parent":null,"children":[],"decl_id":null,"docs":"","sig":null,"attributes":[]},{"kind":"Local","id":{"krate":0,"index":134217731},"span":{"file_name":"src\\main.rs","byte_start":741,"byte_end":744,"line_start":21,"line_end":21,"column_start":17,"column_end":20},"name":"num","qualname":"num$HirId { owner: DefId(0:3 ~ ALDS1_1_A[5943]::main), local_id: 16 }","value":"&u64","parent":null,"children":[],"decl_id":null,"docs":"","sig":null,"attributes":[]}],"impls":[],"refs":[{"kind":"Function","span":{"file_name":"src\\main.rs","byte_start":38,"byte_end":41,"line_start":2,"line_end":2,"column_start":27,"column_end":30},"ref_id":{"krate":5,"index":3899}},{"kind":"Type","span":{"file_name":"src\\main.rs","byte_start":30,"byte_end":36,"line_start":2,"line_end":2,"column_start":19,"column_end":25},"ref_id":{"krate":5,"index":5311}},{"kind":"Function","span":{"file_name":"src\\main.rs","byte_start":86,"byte_end":92,"line_start":3,"line_end":3,"column_start":42,"column_end":48},"ref_id":{"krate":2,"index":6078}},{"kind":"Function","span":{"file_name":"src\\main.rs","byte_start":66,"byte_end":75,"line_start":3,"line_end":3,"column_start":22,"column_end":31},"ref_id":{"krate":1,"index":2872}},{"kind":"Function","span":{"file_name":"src\\main.rs","byte_start":58,"byte_end":63,"line_start":3,"line_end":3,"column_start":14,"column_end":19},"ref_id":{"krate":1,"index":2866}},{"kind":"Mod","span":{"file_name":"src\\main.rs","byte_start":49,"byte_end":52,"line_start":3,"line_end":3,"column_start":5,"column_end":8},"ref_id":{"krate":1,"index":0}},{"kind":"Mod","span":{"file_name":"src\\main.rs","byte_start":54,"byte_end":56,"line_start":3,"line_end":3,"column_start":10,"column_end":12},"ref_id":{"krate":1,"index":2384}},{"kind":"Variable","span":{"file_name":"src\\main.rs","byte_start":81,"byte_end":84,"line_start":3,"line_end":3,"column_start":37,"column_end":40},"ref_id":{"krate":0,"index":2147483651}},{"kind":"Function","span":{"file_name":"src\\main.rs","byte_start":123,"byte_end":126,"line_start":4,"line_end":4,"column_start":28,"column_end":31},"ref_id":{"krate":5,"index":3899}},{"kind":"Type","span":{"file_name":"src\\main.rs","byte_start":115,"byte_end":121,"line_start":4,"line_end":4,"column_start":20,"column_end":26},"ref_id":{"krate":5,"index":5311}},{"kind":"Function","span":{"file_name":"src\\main.rs","byte_start":172,"byte_end":178,"line_start":5,"line_end":5,"column_start":43,"column_end":49},"ref_id":{"krate":2,"index":6078}},{"kind":"Function","span":{"file_name":"src\\main.rs","byte_start":151,"byte_end":160,"line_start":5,"line_end":5,"column_start":22,"column_end":31},"ref_id":{"krate":1,"index":2872}},{"kind":"Function","span":{"file_name":"src\\main.rs","byte_start":143,"byte_end":148,"line_start":5,"line_end":5,"column_start":14,"column_end":19},"ref_id":{"krate":1,"index":2866}},{"kind":"Mod","span":{"file_name":"src\\main.rs","byte_start":134,"byte_end":137,"line_start":5,"line_end":5,"column_start":5,"column_end":8},"ref_id":{"krate":1,"index":0}},{"kind":"Mod","span":{"file_name":"src\\main.rs","byte_start":139,"byte_end":141,"line_start":5,"line_end":5,"column_start":10,"column_end":12},"ref_id":{"krate":1,"index":2384}},{"kind":"Variable","span":{"file_name":"src\\main.rs","byte_start":166,"byte_end":170,"line_start":5,"line_end":5,"column_start":37,"column_end":41},"ref_id":{"krate":0,"index":1073741827}},{"kind":"Type","span":{"file_name":"src\\main.rs","byte_start":205,"byte_end":208,"line_start":7,"line_end":7,"column_start":19,"column_end":22},"ref_id":{"krate":5,"index":4551}},{"kind":"Function","span":{"file_name":"src\\main.rs","byte_start":311,"byte_end":318,"line_start":8,"line_end":8,"column_start":65,"column_end":72},"ref_id":{"krate":2,"index":5343}},{"kind":"Function","span":{"file_name":"src\\main.rs","byte_start":276,"byte_end":279,"line_start":8,"line_end":8,"column_start":30,"column_end":33},"ref_id":{"krate":2,"index":5305}},{"kind":"Function","span":{"file_name":"src\\main.rs","byte_start":228,"byte_end":244,"line_start":7,"line_end":7,"column_start":42,"column_end":58},"ref_id":{"krate":2,"index":8803}},{"kind":"Function","span":{"file_name":"src\\main.rs","byte_start":221,"byte_end":225,"line_start":7,"line_end":7,"column_start":35,"column_end":39},"ref_id":{"krate":2,"index":8864}},{"kind":"Variable","span":{"file_name":"src\\main.rs","byte_start":216,"byte_end":220,"line_start":7,"line_end":7,"column_start":30,"column_end":34},"ref_id":{"krate":0,"index":1073741827}},{"kind":"Function","span":{"file_name":"src\\main.rs","byte_start":301,"byte_end":307,"line_start":8,"line_end":8,"column_start":55,"column_end":61},"ref_id":{"krate":2,"index":6078}},{"kind":"Function","span":{"file_name":"src\\main.rs","byte_start":286,"byte_end":291,"line_start":8,"line_end":8,"column_start":40,"column_end":45},"ref_id":{"krate":2,"index":8893}},{"kind":"Variable","span":{"file_name":"src\\main.rs","byte_start":284,"byte_end":285,"line_start":8,"line_end":8,"column_start":38,"column_end":39},"ref_id":{"krate":0,"index":536870915}},{"kind":"Function","span":{"file_name":"src\\main.rs","byte_start":347,"byte_end":351,"line_start":9,"line_end":9,"column_start":26,"column_end":30},"ref_id":{"krate":2,"index":8045}},{"kind":"Variable","span":{"file_name":"src\\main.rs","byte_start":342,"byte_end":346,"line_start":9,"line_end":9,"column_start":21,"column_end":25},"ref_id":{"krate":0,"index":3221225475}},{"kind":"Variable","span":{"file_name":"src\\main.rs","byte_start":330,"byte_end":338,"line_start":9,"line_end":9,"column_start":9,"column_end":17},"ref_id":{"krate":2,"index":31734}},{"kind":"Function","span":{"file_name":"C:\\Users\\pictu\\.rustup/toolchains/stable-x86_64-pc-windows-msvc\\lib/rustlib/src/rust\\library\\std\\src\\macros.rs","byte_start":23479,"byte_end":23509,"line_start":61,"line_end":61,"column_start":42,"column_end":72},"ref_id":{"krate":2,"index":6551}},{"kind":"Variable","span":{"file_name":"src\\main.rs","byte_start":391,"byte_end":394,"line_start":10,"line_end":10,"column_start":24,"column_end":27},"ref_id":{"krate":0,"index":3758096387}},{"kind":"Variable","span":{"file_name":"src\\main.rs","byte_start":399,"byte_end":400,"line_start":10,"line_end":10,"column_start":32,"column_end":33},"ref_id":{"krate":0,"index":1610612739}},{"kind":"Function","span":{"file_name":"src\\main.rs","byte_start":409,"byte_end":412,"line_start":10,"line_end":10,"column_start":42,"column_end":45},"ref_id":{"krate":5,"index":4596}},{"kind":"Variable","span":{"file_name":"src\\main.rs","byte_start":404,"byte_end":408,"line_start":10,"line_end":10,"column_start":37,"column_end":41},"ref_id":{"krate":0,"index":3221225475}},{"kind":"Function","span":{"file_name":"C:\\Users\\pictu\\.rustup/toolchains/stable-x86_64-pc-windows-msvc\\lib/rustlib/src/rust\\library\\std\\src\\macros.rs","byte_start":23479,"byte_end":23509,"line_start":61,"line_end":61,"column_start":42,"column_end":72},"ref_id":{"krate":2,"index":6544}},{"kind":"Function","span":{"file_name":"C:\\Users\\pictu\\.rustup/toolchains/stable-x86_64-pc-windows-msvc\\lib/rustlib/src/rust\\library\\std\\src\\macros.rs","byte_start":23479,"byte_end":23509,"line_start":61,"line_end":61,"column_start":42,"column_end":72},"ref_id":{"krate":2,"index":6544}},{"kind":"Variable","span":{"file_name":"src\\main.rs","byte_start":465,"byte_end":466,"line_start":13,"line_end":13,"column_start":14,"column_end":15},"ref_id":{"krate":2,"index":30466}},{"kind":"Variable","span":{"file_name":"src\\main.rs","byte_start":468,"byte_end":478,"line_start":13,"line_end":13,"column_start":17,"column_end":27},"ref_id":{"krate":2,"index":30467}},{"kind":"Function","span":{"file_name":"src\\main.rs","byte_start":473,"byte_end":476,"line_start":13,"line_end":13,"column_start":22,"column_end":25},"ref_id":{"krate":5,"index":4596}},{"kind":"Variable","span":{"file_name":"src\\main.rs","byte_start":468,"byte_end":472,"line_start":13,"line_end":13,"column_start":17,"column_end":21},"ref_id":{"krate":0,"index":3221225475}},{"kind":"Variable","span":{"file_name":"src\\main.rs","byte_start":460,"byte_end":461,"line_start":13,"line_end":13,"column_start":9,"column_end":10},"ref_id":{"krate":2,"index":31734}},{"kind":"Variable","span":{"file_name":"src\\main.rs","byte_start":506,"byte_end":507,"line_start":14,"line_end":14,"column_start":26,"column_end":27},"ref_id":{"krate":0,"index":3489660931}},{"kind":"Variable","span":{"file_name":"src\\main.rs","byte_start":541,"byte_end":545,"line_start":15,"line_end":15,"column_start":19,"column_end":23},"ref_id":{"krate":0,"index":3221225475}},{"kind":"Variable","span":{"file_name":"src\\main.rs","byte_start":546,"byte_end":547,"line_start":15,"line_end":15,"column_start":24,"column_end":25},"ref_id":{"krate":0,"index":3489660931}},{"kind":"Variable","span":{"file_name":"src\\main.rs","byte_start":564,"byte_end":565,"line_start":16,"line_end":16,"column_start":15,"column_end":16},"ref_id":{"krate":0,"index":805306371}},{"kind":"Variable","span":{"file_name":"src\\main.rs","byte_start":577,"byte_end":581,"line_start":16,"line_end":16,"column_start":28,"column_end":32},"ref_id":{"krate":0,"index":3221225475}},{"kind":"Variable","span":{"file_name":"src\\main.rs","byte_start":582,"byte_end":583,"line_start":16,"line_end":16,"column_start":33,"column_end":34},"ref_id":{"krate":0,"index":805306371}},{"kind":"Variable","span":{"file_name":"src\\main.rs","byte_start":596,"byte_end":599,"line_start":16,"line_end":16,"column_start":47,"column_end":50},"ref_id":{"krate":0,"index":2952790019}},{"kind":"Variable","span":{"file_name":"src\\main.rs","byte_start":639,"byte_end":643,"line_start":17,"line_end":17,"column_start":38,"column_end":42},"ref_id":{"krate":0,"index":3221225475}},{"kind":"Variable","span":{"file_name":"src\\main.rs","byte_start":644,"byte_end":645,"line_start":17,"line_end":17,"column_start":43,"column_end":44},"ref_id":{"krate":0,"index":805306371}},{"kind":"Variable","span":{"file_name":"src\\main.rs","byte_start":614,"byte_end":618,"line_start":17,"line_end":17,"column_start":13,"column_end":17},"ref_id":{"krate":0,"index":3221225475}},{"kind":"Variable","span":{"file_name":"src\\main.rs","byte_start":620,"byte_end":621,"line_start":17,"line_end":17,"column_start":19,"column_end":20},"ref_id":{"krate":0,"index":805306371}},{"kind":"Variable","span":{"file_name":"src\\main.rs","byte_start":669,"byte_end":670,"line_start":18,"line_end":18,"column_start":13,"column_end":14},"ref_id":{"krate":0,"index":805306371}},{"kind":"Variable","span":{"file_name":"src\\main.rs","byte_start":720,"byte_end":723,"line_start":20,"line_end":20,"column_start":34,"column_end":37},"ref_id":{"krate":0,"index":2952790019}},{"kind":"Variable","span":{"file_name":"src\\main.rs","byte_start":695,"byte_end":699,"line_start":20,"line_end":20,"column_start":9,"column_end":13},"ref_id":{"krate":0,"index":3221225475}},{"kind":"Variable","span":{"file_name":"src\\main.rs","byte_start":701,"byte_end":702,"line_start":20,"line_end":20,"column_start":15,"column_end":16},"ref_id":{"krate":0,"index":805306371}},{"kind":"Function","span":{"file_name":"src\\main.rs","byte_start":754,"byte_end":758,"line_start":21,"line_end":21,"column_start":30,"column_end":34},"ref_id":{"krate":2,"index":8045}},{"kind":"Variable","span":{"file_name":"src\\main.rs","byte_start":749,"byte_end":753,"line_start":21,"line_end":21,"column_start":25,"column_end":29},"ref_id":{"krate":0,"index":3221225475}},{"kind":"Variable","span":{"file_name":"src\\main.rs","byte_start":737,"byte_end":745,"line_start":21,"line_end":21,"column_start":13,"column_end":21},"ref_id":{"krate":2,"index":31734}},{"kind":"Function","span":{"file_name":"C:\\Users\\pictu\\.rustup/toolchains/stable-x86_64-pc-windows-msvc\\lib/rustlib/src/rust\\library\\std\\src\\macros.rs","byte_start":23479,"byte_end":23509,"line_start":61,"line_end":61,"column_start":42,"column_end":72},"ref_id":{"krate":2,"index":6551}},{"kind":"Variable","span":{"file_name":"src\\main.rs","byte_start":802,"byte_end":805,"line_start":22,"line_end":22,"column_start":28,"column_end":31},"ref_id":{"krate":0,"index":134217731}},{"kind":"Variable","span":{"file_name":"src\\main.rs","byte_start":810,"byte_end":811,"line_start":22,"line_end":22,"column_start":36,"column_end":37},"ref_id":{"krate":0,"index":4026531843}},{"kind":"Function","span":{"file_name":"src\\main.rs","byte_start":820,"byte_end":823,"line_start":22,"line_end":22,"column_start":46,"column_end":49},"ref_id":{"krate":5,"index":4596}},{"kind":"Variable","span":{"file_name":"src\\main.rs","byte_start":815,"byte_end":819,"line_start":22,"line_end":22,"column_start":41,"column_end":45},"ref_id":{"krate":0,"index":3221225475}},{"kind":"Function","span":{"file_name":"C:\\Users\\pictu\\.rustup/toolchains/stable-x86_64-pc-windows-msvc\\lib/rustlib/src/rust\\library\\std\\src\\macros.rs","byte_start":23479,"byte_end":23509,"line_start":61,"line_end":61,"column_start":42,"column_end":72},"ref_id":{"krate":2,"index":6544}},{"kind":"Function","span":{"file_name":"C:\\Users\\pictu\\.rustup/toolchains/stable-x86_64-pc-windows-msvc\\lib/rustlib/src/rust\\library\\std\\src\\macros.rs","byte_start":23479,"byte_end":23509,"line_start":61,"line_end":61,"column_start":42,"column_end":72},"ref_id":{"krate":2,"index":6544}}],"macro_refs":[],"relations":[]}